mindflow/__init__.py
mindflow/setup.py
mindflow/cell/__init__.py
mindflow/cell/activation.py
mindflow/cell/attention.py
mindflow/cell/basic_block.py
mindflow/cell/diffusion.py
mindflow/cell/diffusion_transformer.py
mindflow/cell/sno_utils.py
mindflow/cell/unet2d.py
mindflow/cell/utils.py
mindflow/cell/vit.py
mindflow/cell/neural_operators/__init__.py
mindflow/cell/neural_operators/dft.py
mindflow/cell/neural_operators/fno.py
mindflow/cell/neural_operators/kno1d.py
mindflow/cell/neural_operators/kno2d.py
mindflow/cell/neural_operators/m2k.py
mindflow/cell/neural_operators/pdenet.py
mindflow/cell/neural_operators/percnn.py
mindflow/cell/neural_operators/sno.py
mindflow/cell/neural_operators/sp_transform.py
mindflow/cfd/__init__.py
mindflow/cfd/mesh_info.py
mindflow/cfd/runtime.py
mindflow/cfd/simulator.py
mindflow/cfd/utils.py
mindflow/cfd/visualization.py
mindflow/cfd/boundary_conditions/__init__.py
mindflow/cfd/boundary_conditions/base.py
mindflow/cfd/boundary_conditions/boundary_manager.py
mindflow/cfd/boundary_conditions/neumann.py
mindflow/cfd/boundary_conditions/periodic.py
mindflow/cfd/boundary_conditions/symmetry.py
mindflow/cfd/boundary_conditions/wall.py
mindflow/cfd/integrator/__init__.py
mindflow/cfd/integrator/base.py
mindflow/cfd/integrator/euler.py
mindflow/cfd/integrator/runge_kutta3.py
mindflow/cfd/material/__init__.py
mindflow/cfd/material/base.py
mindflow/cfd/material/ideal_gas.py
mindflow/cfd/space_solver/__init__.py
mindflow/cfd/space_solver/godunov_flux.py
mindflow/cfd/space_solver/space_solver.py
mindflow/cfd/space_solver/viscous_flux.py
mindflow/cfd/space_solver/derivative_computer/__init__.py
mindflow/cfd/space_solver/derivative_computer/base.py
mindflow/cfd/space_solver/derivative_computer/forth_order_central_derivative_computer.py
mindflow/cfd/space_solver/derivative_computer/forth_order_face_derivative_computer.py
mindflow/cfd/space_solver/interpolator/__init__.py
mindflow/cfd/space_solver/interpolator/base.py
mindflow_ascend-0.3.0.dist-info/METADATA
mindflow_ascend-0.3.0.dist-info/WHEEL
mindflow_ascend-0.3.0.dist-info/top_level.txt
mindflow_ascend-0.3.0.dist-info/RECORD
