Metadata-Version: 2.4
Name: mindflow_ascend
Version: 0.3.0
Summary: An AI framework for simulations of fluid dynamics
Home-page: https://www.mindspore.cn/
Download-URL: https://gitee.com/mindspore/mindscience/tags
Author: The MindSpore Authors
Author-email: contact@mindspore.cn
License: Apache 2.0
Project-URL: Sources, https://gitee.com/mindspore/mindscience
Project-URL: Issue Tracker, https://gitee.com/mindspore/mindscience/issues
Classifier: License :: OSI Approved :: Apache Software License
Requires-Dist: numpy>=1.17.0
Requires-Dist: scipy>=1.7.0
Requires-Dist: matplotlib>=3.1.3
Requires-Dist: easydict>=1.9
Requires-Dist: sympy>=1.10.1
Dynamic: author
Dynamic: author-email
Dynamic: classifier
Dynamic: download-url
Dynamic: home-page
Dynamic: license
Dynamic: project-url
Dynamic: requires-dist
Dynamic: summary
